behavemae/__init__.py
behavemae/version.py
behavemae-0.0rc1.dist-info/LICENSE
behavemae-0.0rc1.dist-info/METADATA
behavemae-0.0rc1.dist-info/WHEEL
behavemae-0.0rc1.dist-info/top_level.txt
behavemae-0.0rc1.dist-info/RECORD
