Metadata-Version: 2.1
Name: behavemae
Version: 0.0rc1
Summary: Elucidating the Hierarchical Nature of Behavior with Masked Autoencoders
Home-page: https://github.com/amathislab/BehaveMAE
Author: Lucas Stoffl, Andy Bonnetto, "Stéphane d'Ascoli", Alexander Mathis
Author-email: alexander.mathis@epfl.ch
Requires-Python: >=3.10
License-File: LICENSE
Requires-Dist: numpy<2.0.0,>=1.26.4
Requires-Dist: scikit-learn>=1.5.1
Requires-Dist: scipy>=1.12.0
Requires-Dist: tensorboard>=2.17.0
Requires-Dist: timm>=1.0.8
Requires-Dist: torch>=2.0.0
Requires-Dist: torchvision>=0.15.2
Requires-Dist: tqdm>=4.66.4
Provides-Extra: dev
Requires-Dist: pylint; extra == "dev"
Requires-Dist: toml; extra == "dev"
Requires-Dist: yapf; extra == "dev"
Requires-Dist: black; extra == "dev"
Requires-Dist: pytest; extra == "dev"
